rawr/__init__.py
rawr/rawr.py
rawr_cli-0.0.2.dist-info/entry_points.txt
rawr_cli-0.0.2.dist-info/LICENSE
rawr_cli-0.0.2.dist-info/WHEEL
rawr_cli-0.0.2.dist-info/METADATA
rawr_cli-0.0.2.dist-info/RECORD
