Metadata-Version: 2.1
Name: rawr-cli
Version: 0.0.2
Summary: A basic CLI for finding and downloading torrents with rarbgapi and aria2
Home-page: https://github.com/andydecleyre/rawr
License: WTFPL
Keywords: rarbg,rarbgapi,torrent,cli
Author: Andy Kluger
Requires-Python: >=3.6
Requires-Dist: plumbum
Requires-Dist: rarbgapi>=0.4.1
Requires-Dist: flit ; extra == "dev"
Provides-Extra: dev
